dlinc_didkit-0.1.0.dist-info/METADATA
dlinc_didkit-0.1.0.dist-info/WHEEL
dlinc_didkit-0.1.0.dist-info/license_files/LICENSE
didkit/__init__.py
didkit/py.typed
didkit/didkit.pyi
didkit/didkit.cpython-310-darwin.so
dlinc_didkit-0.1.0.dist-info/RECORD
