Metadata-Version: 2.1
Name: dlinc-didkit
Version: 0.1.0
Classifier: Programming Language :: Rust
Classifier: Programming Language :: Python :: Implementation :: CPython
Classifier: Programming Language :: Python :: Implementation :: PyPy
Classifier: Topic :: Security
License-File: LICENSE
Summary: Fork of spruceid/didkit-python maintained by dLinc. Library for Verifiable Credentials and Decentralized Identifiers.
Keywords: ssi,did,python
Home-Page: https://spruceid.dev/docs/didkit/
Author: Spruce Systems, Inc.
License: Apache-2.0
Requires-Python: >=3.7
Project-URL: Issues, https://github.com/dogwoodlogic/didkit-python/issues
Project-URL: Homepage, https://github.com/dogwoodlogic/didkit-python
Project-URL: Upstream, https://github.com/spruceid/didkit-python
Project-URL: Source, https://github.com/dogwoodlogic/didkit-python
